track_generator/__init__.py
track_generator/__main__.py
track_generator/_version.py
track_generator/coordinate_system.py
track_generator/gazebo_model_generator.py
track_generator/generator.py
track_generator/ground_truth_generator.py
track_generator/painter.py
track_generator/starter.py
track_generator/track.py
track_generator/xml_reader.py
track_generator/gui/__init__.py
track_generator/gui/track_live_view.py
track_generator/gui/qml/track_live_view.qml
track_generator/segment_templates/crosswalk.svg
track_generator/segment_templates/intersection.svg
track_generator/xsd/track.xsd
track_generator-0.6.0.dist-info/METADATA
track_generator-0.6.0.dist-info/WHEEL
track_generator-0.6.0.dist-info/entry_points.txt
track_generator-0.6.0.dist-info/top_level.txt
track_generator-0.6.0.dist-info/RECORD
