Metadata-Version: 2.1
Name: track-generator
Version: 0.6.0
Summary: Track generator
Home-page: https://github.com/twyleg/track_generator
Author: Torsten Wylegala
Author-email: mail@twyleg.de
License: GPL 3.0
Keywords: svg model vehicles track
Requires-Dist: pytransform3d ~=3.2.0
Requires-Dist: drawsvg[all] ~=2.2.0
Requires-Dist: watchdog ~=3.0.0
Requires-Dist: pyside6 >=6.2.4
Requires-Dist: xmlschema ~=2.3.1
Requires-Dist: jinja2 ~=3.1.2
